nfn/__init__.py
nfn/common/__init__.py
nfn/common/data.py
nfn/layers/__init__.py
nfn/layers/encoding.py
nfn/layers/layer_utils.py
nfn/layers/layers.py
nfn/layers/misc_layers.py
nfn/layers/regularize.py
tests/__init__.py
tests/test_layers.py
nfn-0.1.2.dist-info/LICENSE
nfn-0.1.2.dist-info/METADATA
nfn-0.1.2.dist-info/WHEEL
nfn-0.1.2.dist-info/top_level.txt
nfn-0.1.2.dist-info/RECORD
